jupyter_plane/__init__.py
jupyter_plane/_version.py
jupyter_plane/handlers.py
jupyter_plane/tests/__init__.py
jupyter_plane/tests/test_handlers.py
jupyter_plane-0.0.3.data/data/etc/jupyter/jupyter_notebook_config.d/jupyter_plane.json
jupyter_plane-0.0.3.data/data/etc/jupyter/jupyter_server_config.d/jupyter_plane.json
jupyter_plane-0.0.3.data/data/share/jupyter/labextensions/@datalayer/jupyter-plane/build_log.json
jupyter_plane-0.0.3.data/data/share/jupyter/labextensions/@datalayer/jupyter-plane/package.json
jupyter_plane-0.0.3.data/data/share/jupyter/labextensions/@datalayer/jupyter-plane/schemas/@datalayer/jupyter-plane/package.json.orig
jupyter_plane-0.0.3.data/data/share/jupyter/labextensions/@datalayer/jupyter-plane/schemas/@datalayer/jupyter-plane/plugin.json
jupyter_plane-0.0.3.data/data/share/jupyter/labextensions/@datalayer/jupyter-plane/static/design_icons_lib_index_js.f2108be60941173b96ef.js
jupyter_plane-0.0.3.data/data/share/jupyter/labextensions/@datalayer/jupyter-plane/static/design_icons_lib_index_js.f2108be60941173b96ef.js.map
jupyter_plane-0.0.3.data/data/share/jupyter/labextensions/@datalayer/jupyter-plane/static/lib_index_js.21445b857e6a4ae8c9df.js
jupyter_plane-0.0.3.data/data/share/jupyter/labextensions/@datalayer/jupyter-plane/static/lib_index_js.21445b857e6a4ae8c9df.js.map
jupyter_plane-0.0.3.data/data/share/jupyter/labextensions/@datalayer/jupyter-plane/static/node_modules_object-assign_index_js.35aebf3a5897ef19bdf6.js
jupyter_plane-0.0.3.data/data/share/jupyter/labextensions/@datalayer/jupyter-plane/static/node_modules_object-assign_index_js.35aebf3a5897ef19bdf6.js.map
jupyter_plane-0.0.3.data/data/share/jupyter/labextensions/@datalayer/jupyter-plane/static/remoteEntry.455296f87eca5203045c.js
jupyter_plane-0.0.3.data/data/share/jupyter/labextensions/@datalayer/jupyter-plane/static/remoteEntry.455296f87eca5203045c.js.map
jupyter_plane-0.0.3.data/data/share/jupyter/labextensions/@datalayer/jupyter-plane/static/style.js
jupyter_plane-0.0.3.dist-info/METADATA
jupyter_plane-0.0.3.dist-info/WHEEL
jupyter_plane-0.0.3.dist-info/licenses/LICENSE
jupyter_plane-0.0.3.dist-info/RECORD
